save/__init__.py
save/main.py
save_text-1.3.2.dist-info/METADATA
save_text-1.3.2.dist-info/WHEEL
save_text-1.3.2.dist-info/entry_points.txt
save_text-1.3.2.dist-info/top_level.txt
save_text-1.3.2.dist-info/RECORD
