Metadata-Version: 2.1
Name: save-text
Version: 1.3.2
Summary: You can save and retrieve text.
Home-page: https://github.com/YahiroRyo
Author: YahiroRyo
Author-email: YahiroRyo@users.noreply.github.com
License: MIT
Platform: UNKNOWN
Classifier: Programming Language :: Python :: 3
Classifier: License :: OSI Approved :: MIT License
Classifier: Operating System :: OS Independent
